sum_netapp_demo/__init__.py
sum_netapp_demo-0.0.1.dist-info/LICENSE
sum_netapp_demo-0.0.1.dist-info/METADATA
sum_netapp_demo-0.0.1.dist-info/WHEEL
sum_netapp_demo-0.0.1.dist-info/top_level.txt
sum_netapp_demo-0.0.1.dist-info/RECORD
