Metadata-Version: 2.1
Name: sum-netapp-demo
Version: 0.0.1
Summary: adding number
Home-page: https://github.com/Pushkar-Singh-14/
Author: Sahil Arora
Author-email: sarora160@gmail.com
License: UNKNOWN
Platform: UNKNOWN
Classifier: Programming Language :: Python :: 3
Classifier: License :: OSI Approved :: MIT License
Classifier: Operating System :: OS Independent
